fango/auth.py
fango/pagination.py
fango/request.py
fango/routing.py
fango/schemas.py
fango/utils.py
fango/viewsets.py
fango-0.1.7.dist-info/METADATA
fango-0.1.7.dist-info/WHEEL
fango-0.1.7.dist-info/RECORD
