Metadata-Version: 2.1
Name: fango
Version: 0.1.7
Summary: Metaframework for web with combined FastAPI and Django
Home-page: https://github.com/egorgam/fango
License: MIT
Keywords: fastapi,django,fango
Author: Egor Gamazin
Author-email: egorgamazin@yandex.ru
Requires-Python: >=3.10,<4.0
Classifier: License :: OSI Approved :: MIT License
Classifier: Programming Language :: Python :: 3
Classifier: Programming Language :: Python :: 3.10
Classifier: Programming Language :: Python :: 3.11
Classifier: Programming Language :: Python :: 3.12
Requires-Dist: django (>=4.2,<6.0)
Requires-Dist: fastapi (>=0.108.0,<0.109.0)
Requires-Dist: python-jose (>=3.3.0,<4.0.0)
Project-URL: Repository, https://github.com/egorgam/fango
